load_distribution/__init__.py
load_distribution/geom_ops.py
load_distribution/load_distribution.py
load_distribution-0.1.7.dist-info/licenses/LICENSE
load_distribution-0.1.7.dist-info/WHEEL
load_distribution-0.1.7.dist-info/METADATA
load_distribution-0.1.7.dist-info/RECORD
