Metadata-Version: 2.4
Name: load-distribution
Version: 0.1.7
Summary: A package for converting arbitrary polygons into linearly distributed
Author-email: Connor Ferster <connor@structuralpython.com>
Requires-Python: >=3.11
License-File: LICENSE
Requires-Dist: numpy>=2.0.0
Requires-Dist: shapely>=2.0.0
